[{
    "name": "Compress image to 1.2mb",
    "url": "/compress-image-to-1-2-mb"
},
{
    "name": "Compress image to 1.3mb",
    "url": "/compress-image-to-1-3-mb"
},
{
    "name": "Compress image to 1.8kb",
    "url": "/compress-image-to-1-8-kb"
},
{
    "name": "Compress image to 1mb",
    "url": "/compress-image-to-1-mb"
},
{
    "name": "Compress image to 2.4kb",
    "url": "/compress-image-to-2-4-kb"
},
{
    "name": "Compress image to 2.6mb",
    "url": "/compress-image-to-2-6-mb"
},
{
    "name": "Compress image to 2mb",
    "url": "/compress-image-to-2-mb"
},{   "name": "compress image to 1.5mb ",
    "url": "/compress-image-to-1-5-mb"
},
{
    "name": "compress image to 5mb ",
    "url": "/compress-image-to-5-mb"
},
{
    "name": "compress image to 10mb ",
    "url": "/compress-image-to-10-mb"
},
{
    "name": "compress image to 3mb ",
    "url": "/compress-image-to-3-mb"
},
{
    "name": "compress image to 20mb ",
    "url": "/compress-image-to-20-mb"
},
{
    "name": "compress image to 1.8mb ",
    "url": "/compress-image-to-1-8-mb"
},
{
    "name": "compress image to 8mb ",
    "url": "/compress-image-to-8-mb"
},
{
    "name": "compress image to 4mb ",
    "url": "/compress-image-to-4-mb"
},
{
    "name": "Compress image to 3.5mb",
    "url": "/compress-image-to-3-5-mb"
},
{
    "name": "Compress image to 3kb",
    "url": "/compress-image-to-3-kb"
},
{
    "name": "Compress image to 4.4kb",
    "url": "/compress-image-to-4-4-kb"
},
{
    "name": "Compress image to 6kb",
    "url": "/compress-image-to-6-kb"
},
{
    "name": "Compress image to 6mb",
    "url": "/compress-image-to-6-mb"
},
{
    "name": "Compress image to 8kb",
    "url": "/compress-image-to-8-kb"
},
{
    "name": "Compress image to 9kb",
    "url": "/compress-image-to-9-kb"
},
{
    "name": "Compress image to 11.8kb",
    "url": "/compress-image-to-11-8-kb"
},
{
    "name": "Compress image to 15kb",
    "url": "/compress-image-to-15-kb"
},
{
    "name": "Compress image to 20kb",
    "url": "/compress-image-to-20-kb"
},
{
    "name": "Compress image to 25kb",
    "url": "/compress-image-to-25-kb"
},
{
    "name": "Compress image to 27kb",
    "url": "/compress-image-to-27-kb"
},
{
    "name": "Compress image to 30kb",
    "url": "/compress-image-to-30-kb"
},
{
    "name": "Compress image to 50kb",
    "url": "/compress-image-to-50-kb"
},
{
    "name": "Compress image to 71kb",
    "url": "/compress-image-to-71-kb"
},
{
    "name": "Compress image to 79kb",
    "url": "/compress-image-to-79-kb"
},
{
    "name": "Compress image to 100kb",
    "url": "/compress-image-to-100-kb"
},
{
    "name": "Compress image to 173kb",
    "url": "/compress-image-to-173-kb"
},
{
    "name": "Compress image to 200kb",
    "url": "/compress-image-to-200-kb"
},
{
    "name": "Compress image to 240kb",
    "url": "/compress-image-to-240-kb"
},
{
    "name": "Compress image to 256kb",
    "url": "/compress-image-to-256-kb"
},
{
    "name": "Compress image to 299kb",
    "url": "/compress-image-to-299-kb"
},
{
    "name": "Compress image to 300kb",
    "url": "/compress-image-to-300-kb"
},
{
    "name": "Compress image to 399kb",
    "url": "/compress-image-to-399-kb"
},
{
    "name": "Compress image to 414kb",
    "url": "/compress-image-to-414-kb"
},
{
    "name": "Compress image to 425kb",
    "url": "/compress-image-to-425-kb"
},
{
    "name": "Compress image to 480kb",
    "url": "/compress-image-to-480-kb"
},
{
    "name": "Compress image to 500kb",
    "url": "/compress-image-to-500-kb"
},
{
    "name": "Compress image to 600kb",
    "url": "/compress-image-to-720-kb"
},
{
    "name": "Compress image to 2kb",
    "url": "/compress-image-to-2-kb"
}, {
    "name": "Compress image to 3kb",
    "url": "/compress-image-to-3-kb"
}, {
    "name": "Compress image to 4kb",
    "url": "/compress-image-to-4-kb"
}, {
    "name": "Compress image to 5kb",
    "url": "/compress-image-to-5-kb"
}, {
    "name": "Compress image to 6kb",
    "url": "/compress-image-to-6-kb"
}, {
    "name": "Compress image to 9kb",
    "url": "/compress-image-to-9-kb"
}, {
    "name": "Compress image to 10kb",
    "url": "/compress-image-to-10-kb"
}, {
    "name": "Compress image to 12kb",
    "url": "/compress-image-to-12-kb"
}, {
    "name": "Compress image to 15kb",
    "url": "/compress-image-to-15-kb"
}, {
    "name": "Compress image to 16kb",
    "url": "/compress-image-to-16-kb"
}, {
    "name": "Compress image to 17kb",
    "url": "/compress-image-to-17-kb"
}, {
    "name": "Compress image to 18kb",
    "url": "/compress-image-to-18-kb"
}, {
    "name": "Compress image to 19kb",
    "url": "/compress-image-to-19-kb"
}, {
    "name": "Compress image to 20kb",
    "url": "/compress-image-to-20-kb"
}, {
    "name": "Compress image to 22kb",
    "url": "/compress-image-to-22-kb"
}, {
    "name": "Compress image to 24kb",
    "url": "/compress-image-to-24-kb"
}, {
    "name": "Compress image to 25kb",
    "url": "/compress-image-to-25-kb"
}, {
    "name": "Compress image to 30kb",
    "url": "/compress-image-to-30-kb"
}, {
    "name": "Compress image to 35kb",
    "url": "/compress-image-to-35-kb"
}, {
    "name": "Compress image to 40kb",
    "url": "/compress-image-to-40-kb"
}, {
    "name": "Compress image to 45kb",
    "url": "/compress-image-to-45-kb"
}, {
    "name": "Compress image to 50kb",
    "url": "/compress-image-to-50-kb"
}, {
    "name": "Compress image to 60kb",
    "url": "/compress-image-to-60-kb"
}, {
    "name": "Compress image to 64kb",
    "url": "/compress-image-to-64-kb"
}, {
    "name": "Compress image to 70kb",
    "url": "/compress-image-to-70-kb"
}, {
    "name": "Compress image to 75kb",
    "url": "/compress-image-to-75-kb"
}, {
    "name": "Compress image to 80kb",
    "url": "/compress-image-to-80-kb"
}, {
    "name": "Compress image to 90kb",
    "url": "/compress-image-to-90-kb"
}, {
    "name": "Compress image to 100kb",
    "url": "/compress-image-to-100-kb"
}, {
    "name": "Compress image to 120kb",
    "url": "/compress-image-to-120-kb"
}, {
    "name": "Compress image to 130kb",
    "url": "/compress-image-to-130-kb"
}, {
    "name": "Compress image to 140kb",
    "url": "/compress-image-to-140-kb"
}, {
    "name": "Compress image to 150kb",
    "url": "/compress-image-to-150-kb"
}, {
    "name": "Compress image to 180kb",
    "url": "/compress-image-to-180-kb"
}, {
    "name": "Compress image to 200kb",
    "url": "/compress-image-to-200-kb"
}, {
    "name": "Compress image to 220kb",
    "url": "/compress-image-to-220-kb"
}, {
    "name": "Compress image to 228kb",
    "url": "/compress-image-to-228-kb"
}, {
    "name": "Compress image to 250kb",
    "url": "/compress-image-to-250-kb"
}, {
    "name": "Compress image to 256kb",
    "url": "/compress-image-to-256-kb"
}, {
    "name": "Compress image to 300kb",
    "url": "/compress-image-to-300-kb"
}, {
    "name": "Compress image to 350kb",
    "url": "/compress-image-to-350-kb"
}, {
    "name": "Compress image to 388kb",
    "url": "/compress-image-to-388-kb"
}, {
    "name": "Compress image to 400kb",
    "url": "/compress-image-to-400-kb"
}, {
    "name": "Compress image to 450kb",
    "url": "/compress-image-to-450-kb"
}, {
    "name": "Compress image to 480kb",
    "url": "/compress-image-to-480-kb"
}, {
    "name": "Compress image to 500kb",
    "url": "/compress-image-to-500-kb"
}, {
    "name": "Compress image to 510kb",
    "url": "/compress-image-to-510-kb"
}, {
    "name": "Compress image to 512kb",
    "url": "/compress-image-to-512-kb"
}, {
    "name": "Compress image to 600kb",
    "url": "/compress-image-to-600-kb"
}, {
    "name": "Compress image to 800kb",
    "url": "/compress-image-to-800-kb"
}, {
    "name": "Compress image to 1024kb",
    "url": "/compress-image-to-1024-kb"
}
]