{
    "Language": "ภาษาไทย",
    "htmlLangAtt": "th",
    "H1": "ออนไลน์ฟรี 12x18 ขนาดภาพปรับขนาดเป็นนิ้ว",
    "keywords": "ปรับขนาดภาพเป็น 12x18",
    "img": "/img/resize.png",
    "imgwidth": "35px",
    "imgheight": "35px",
    "imgalt": "altvalue",
    "nofileupload": true,
    "variant": "เตือน",
    "H2": "เครื่องมือที่ดีที่สุดสำหรับการปรับขนาดภาพเป็น 12x18 ขนาดได้อย่างรวดเร็ว",
    "TITLE": "ปรับขนาดภาพเป็น 12x18 ขนาดเป็นนิ้วโดยไม่สูญเสียคุณภาพ - เครื่องมือออนไลน์ฟรีที่ดีที่สุด",
    "META": "ปรับขนาดภาพของคุณเป็นอัตราส่วน 12x18 ได้ทันทีโดยไม่สูญเสียคุณภาพเครื่องมือปรับขนาดภาพ 12x18 ฟรีนี้ช่วยให้คุณสามารถดาวน์โหลดภาพที่มีการปรับขนาดในรูปแบบ JPG, JPEG, PNG และ WEBP โดยไม่ต้องลงชื่อเข้าใช้ ",
    "LABEL": "",
    "BREADCRUMB_LABEL": "",
    "color": "#0D66D0",
    "megaMenu": {
        "nav-link-name": "Tools",
        "dropdown": [
            {
                "categoryName": "ภาพอยู่ในนิ้ว",
                "links": [
                    {
                        "name": "ปรับขนาดภาพเป็น 3x5 ",
                        "iconSrc": "/img/resize.png",
                        "url": "/th/resize-image-to-3x5"
                    },
                    {
                        "name": "ปรับขนาดภาพเป็น 4x6 ",
                        "iconSrc": "/img/resize.png",
                        "url": "/th/resize-image-to-4x6"
                    },
                    {
                        "name": "ปรับขนาดภาพเป็น 5x7 ",
                        "iconSrc": "/img/resize.png",
                        "url": "/th/resize-image-to-5x7"
                    },
                    {
                        "name": "ปรับขนาดภาพเป็น 8x8",
                        "iconSrc": "/img/resize.png",
                        "url": "/th/resize-image-to-8x8"
                    },
                    {
                        "name": "ปรับขนาดภาพเป็น 8x10 ",
                        "iconSrc": "/img/resize.png",
                        "url": "/th/resize-image-to-8x10"
                    },
                    {
                        "name": "ปรับขนาดภาพเป็น 8x11 ",
                        "iconSrc": "/img/resize.png",
                        "url": "/th/resize-image-to-8x11"
                    },
                    {
                        "name": "ปรับขนาดภาพเป็น 2x2 ",
                        "iconSrc": "/img/resize.png",
                        "url": "/th/resize-image-to-2x2"
                    },
                    {
                        "name": "ปรับขนาดภาพเป็น 9x16 ",
                        "iconSrc": "/img/resize.png",
                        "url": "/th/resize-image-to-9x16"
                    },
                    {
                        "name": "ปรับขนาดภาพเป็น 11x14 ",
                        "iconSrc": "/img/resize.png",
                        "url": "/th/resize-image-to-11x14"
                    },
                    {
                        "name": "ปรับขนาดภาพเป็น 11x16 ",
                        "iconSrc": "/img/resize.png",
                        "url": "/th/resize-image-to-11x16"
                    },
                    {
                        "name": "ปรับขนาดภาพเป็น 12x18 ",
                        "iconSrc": "/img/resize.png",
                        "url": "/th/resize-image-to-12x18"
                    },
                    {
                        "name": "ปรับขนาดภาพเป็น 18x24 ",
                        "iconSrc": "/img/resize.png",
                        "url": "/th/resize-image-to-18x24"
                    },
                    {
                        "name": "ปรับขนาดภาพเป็น 18x36 ",
                        "iconSrc": "/img/resize.png",
                        "url": "/th/resize-image-to-18x36"
                    },
                    {
                        "name": "ปรับขนาดภาพเป็น 20x24 ",
                        "iconSrc": "/img/resize.png",
                        "url": "/th/resize-image-to-20x24"
                    },
                    {
                        "name": "ปรับขนาดภาพเป็น 24x36 ",
                        "iconSrc": "/img/resize.png",
                        "url": "/th/resize-image-to-24x36"
                    },
                    {
                        "name": "ปรับขนาดภาพเป็น 24x30 ",
                        "iconSrc": "/img/resize.png",
                        "url": "/th/resize-image-to-24x30"
                    },
                    {
                        "name": "ปรับขนาดภาพเป็น 24x48 ",
                        "iconSrc": "/img/resize.png",
                        "url": "/th/resize-image-to-24x48"
                    },
                    {
                        "name": "ปรับขนาดภาพเป็น 29x21 ",
                        "iconSrc": "/img/resize.png",
                        "url": "/th/resize-image-to-29x21"
                    },
                    {
                        "name": "ปรับขนาดภาพเป็น 30x36 ",
                        "iconSrc": "/img/resize.png",
                        "url": "/th/resize-image-to-30x36"
                    },
                    {
                        "name": "ปรับขนาดภาพเป็น 30x40 ",
                        "iconSrc": "/img/resize.png",
                        "url": "/th/resize-image-to-30x40"
                    }
                ]
            },
            {
                "categoryName": "ภาพอยู่ในพิกเซล",
                "links": [
                    {
                        "name": "ปรับขนาดภาพเป็น 900x1500 ",
                        "iconSrc": "/img/resize.png",
                        "url": "/th/resize-image-to-900x1500"
                    },
                    {
                        "name": "ปรับขนาดภาพเป็น 1200x1800 ",
                        "iconSrc": "/img/resize.png",
                        "url": "/th/resize-image-to-1200x1800"
                    },
                    {
                        "name": "ปรับขนาดภาพเป็น 32x32 ",
                        "iconSrc": "/img/resize.png",
                        "url": "/th/resize-image-to-32x32"
                    },
                    {
                        "name": "ปรับขนาดภาพเป็น 42x59 ",
                        "iconSrc": "/img/resize.png",
                        "url": "/th/resize-image-to-42x59"
                    },
                    {
                        "name": "ปรับขนาดภาพเป็น 128x128 ",
                        "iconSrc": "/img/resize.png",
                        "url": "/th/resize-image-to-128x128"
                    },
                    {
                        "name": "ปรับขนาดภาพเป็น 21x29 ",
                        "iconSrc": "/img/resize.png",
                        "url": "/th/resize-image-to-21x29"
                    },
                    {
                        "name": "ปรับขนาดภาพเป็น 150x150 ",
                        "iconSrc": "/img/resize.png",
                        "url": "/th/resize-image-to-150x150"
                    },
                    {
                        "name": "ปรับขนาดภาพเป็น 168x168 ",
                        "iconSrc": "/img/resize.png",
                        "url": "/th/resize-image-to-168x168"
                    },
                    {
                        "name": "ปรับขนาดภาพเป็น 170x170 ",
                        "iconSrc": "/img/resize.png",
                        "url": "/th/resize-image-to-170x170"
                    },
                    {
                        "name": "ปรับขนาดภาพเป็น 254x94 ",
                        "iconSrc": "/img/resize.png",
                        "url": "/th/resize-image-to-254x94"
                    },
                    {
                        "name": "ปรับขนาดภาพเป็น 266x177 ",
                        "iconSrc": "/img/resize.png",
                        "url": "/th/resize-image-to-266x177"
                    },
                    {
                        "name": "ปรับขนาดภาพเป็น 300x300 ",
                        "iconSrc": "/img/resize.png",
                        "url": "/th/resize-image-to-300x300"
                    },
                    {
                        "name": "ปรับขนาดภาพเป็น 320x320 ",
                        "iconSrc": "/img/resize.png",
                        "url": "/th/resize-image-to-320x320"
                    },
                    {
                        "name": "ปรับขนาดภาพเป็น 385x256 ",
                        "iconSrc": "/img/resize.png",
                        "url": "/th/resize-image-to-385x256"
                    },
                    {
                        "name": "ปรับขนาดภาพเป็น 450x450 ",
                        "iconSrc": "/img/resize.png",
                        "url": "/th/resize-image-to-450x450"
                    },
                    {
                        "name": "ปรับขนาดภาพเป็น 500x500 ",
                        "iconSrc": "/img/resize.png",
                        "url": "/th/resize-image-to-500x500"
                    },
                    {
                        "name": "ปรับขนาดภาพเป็น 560x208 ",
                        "iconSrc": "/img/resize.png",
                        "url": "/th/resize-image-to-560x208"
                    },
                    {
                        "name": "ปรับขนาดภาพเป็น 630x1200 ",
                        "iconSrc": "/img/resize.png",
                        "url": "/th/resize-image-to-630x1200"
                    },
                    {
                        "name": "ปรับขนาดภาพเป็น 700x800 ",
                        "iconSrc": "/img/resize.png",
                        "url": "/th/resize-image-to-700x800"
                    },
                    {
                        "name": "ปรับขนาดภาพเป็น 800x2000 ",
                        "iconSrc": "/img/resize.png",
                        "url": "/th/resize-image-to-800x2000"
                    },
                    {
                        "name": "ปรับขนาดภาพเป็น 900x1500 ",
                        "iconSrc": "/img/resize.png",
                        "url": "/th/resize-image-to-900x1500"
                    },
                    {
                        "name": "ปรับขนาดภาพเป็น 1000x524 ",
                        "iconSrc": "/img/resize.png",
                        "url": "/th/resize-image-to-1000x524"
                    },
                    {
                        "name": "ปรับขนาดภาพเป็น 1000x1000 ",
                        "iconSrc": "/img/resize.png",
                        "url": "/th/resize-image-to-1000x1000"
                    },
                    {
                        "name": "ปรับขนาดภาพเป็น 1024x768 ",
                        "iconSrc": "/img/resize.png",
                        "url": "/th/resize-image-to-1024x768"
                    },
                    {
                        "name": "ปรับขนาดภาพเป็น 1080x1920 ",
                        "iconSrc": "/img/resize.png",
                        "url": "/th/resize-image-to-1080x1920"
                    },
                    {
                        "name": "ปรับขนาดภาพเป็น 1080x1080 ",
                        "iconSrc": "/img/resize.png",
                        "url": "/th/resize-image-to-1080x1080"
                    },
                    {
                        "name": "ปรับขนาดภาพเป็น 1080x1350 ",
                        "iconSrc": "/img/resize.png",
                        "url": "/th/resize-image-to-1080x1350"
                    },
                    {
                        "name": "ปรับขนาดภาพเป็น 1200x628 ",
                        "iconSrc": "/img/resize.png",
                        "url": "/th/resize-image-to-1200x628"
                    },
                    {
                        "name": "ปรับขนาดภาพเป็น 1200x630 ",
                        "iconSrc": "/img/resize.png",
                        "url": "/th/resize-image-to-1200x630"
                    },
                    {
                        "name": "ปรับขนาดภาพเป็น 1200x675 ",
                        "iconSrc": "/img/resize.png",
                        "url": "/th/resize-image-to-1200x675"
                    },
                    {
                        "name": "ปรับขนาดภาพเป็น 1200x1200 ",
                        "iconSrc": "/img/resize.png",
                        "url": "/th/resize-image-to-1200x1200"
                    },
                    {
                        "name": "ปรับขนาดภาพเป็น 1200x1800 ",
                        "iconSrc": "/img/resize.png",
                        "url": "/th/resize-image-to-1200x1800"
                    },
                    {
                        "name": "ปรับขนาดภาพเป็น 1280x720 ",
                        "iconSrc": "/img/resize.png",
                        "url": "/th/resize-image-to-1280x720"
                    },
                    {
                        "name": "ปรับขนาดภาพเป็น 1500x2100 ",
                        "iconSrc": "/img/resize.png",
                        "url": "/th/resize-image-to-1500x2100"
                    },
                    {
                        "name": "ปรับขนาดภาพเป็น 1584x396 ",
                        "iconSrc": "/img/resize.png",
                        "url": "/th/resize-image-to-1584x396"
                    },
                    {
                        "name": "ปรับขนาดภาพเป็น 1640x923 ",
                        "iconSrc": "/img/resize.png",
                        "url": "/th/resize-image-to-1640x923"
                    },
                    {
                        "name": "ปรับขนาดภาพเป็น 1920x480 ",
                        "iconSrc": "/img/resize.png",
                        "url": "/th/resize-image-to-1920x480"
                    },
                    {
                        "name": "ปรับขนาดภาพเป็น 1920x1080 ",
                        "iconSrc": "/img/resize.png",
                        "url": "/th/resize-image-to-1920x1080"
                    },
                    {
                        "name": "ปรับขนาดภาพเป็น 1958x745 ",
                        "iconSrc": "/img/resize.png",
                        "url": "/th/resize-image-to-1958x745"
                    },
                    {
                        "name": "ปรับขนาดภาพเป็น 2037x754 ",
                        "iconSrc": "/img/resize.png",
                        "url": "/th/resize-image-to-2037x754"
                    },
                    {
                        "name": "ปรับขนาดภาพเป็น 2400x3000 ",
                        "iconSrc": "/img/resize.png",
                        "url": "/th/resize-image-to-2400x3000"
                    },
                    {
                        "name": "ปรับขนาดภาพเป็น 2550x3300 ",
                        "iconSrc": "/img/resize.png",
                        "url": "/th/resize-image-to-2550x3300"
                    },
                    {
                        "name": "ปรับขนาดภาพเป็น 2700x4800 ",
                        "iconSrc": "/img/resize.png",
                        "url": "/th/resize-image-to-2700x4800"
                    },
                    {
                        "name": "ปรับขนาดภาพเป็น 3300x4200 ",
                        "iconSrc": "/img/resize.png",
                        "url": "/th/resize-image-to-3300x4200"
                    },
                    {
                        "name": "ปรับขนาดภาพเป็น 3300x4800 ",
                        "iconSrc": "/img/resize.png",
                        "url": "/th/resize-image-to-3300x4800"
                    }
                ]
            }
        ]
    },
    "TEXTUAL_CONTENT": [
        {
            "priority": 1,
            "logoUrl": "/img/featureproperty/highquality.png",
            "header": "รักษาคุณภาพของภาพให้อยู่ในระดับสูง",
            "content": "มันเป็นไปได้ที่จะปรับขนาดภาพเป็นนิ้วโดยไม่สูญเสียคุณภาพของพวกเขาด้วยความช่วยเหลือของภาพ resizer ของเราเป็นเครื่องมือขนาด 12x18อัตราส่วนภาพของภาพขยายจะเหมือนกับของภาพต้นฉบับไม่มีข้อกำหนดด้านเทคโนโลยีและแม้แต่ผู้ใช้ที่ไม่ใช่ด้านเทคนิคก็สามารถดำเนินการตามขั้นตอนได้นอกจากนี้ยังให้ตัวอย่างภาพที่มีการปรับขนาดเพื่อให้คุณดำเนินการขั้นตอนการปรับขนาดได้อย่างราบรื่นที่สุดเท่าที่จะเป็นไปได้"
        },
        {
            "priority": 1,
            "logoUrl": "/img/featureproperty/flexible.png",
            "header": "ใช้งานง่าย",
            "content": "เครื่องมือปรับขนาดภาพ 12x18 ขนาดเป็นนิ้วเป็นเรื่องง่ายมากที่จะใช้งาน.แรกและสำคัญที่สุด UI เป็นเรื่องง่ายและตรงไปตรงมาเนื่องจากความจริงที่ว่าทุกอย่างอยู่ในจุดเดียวคุณจะไม่ต้องคาดเดาว่าจะเริ่มแก้ไขที่ไหนนอกจากนี้ เครื่องมือ resizer image to 12x18 มิติ ยังไม่มีโฆษณาใดๆ ซึ่งส่งผลให้เกิดประสบการณ์การใช้งานที่น่าพอใจยิ่งขึ้นสำหรับผู้ใช้ปลายทาง"
        },
        {
            "priority": 1,
            "logoUrl": "/img/featureproperty/security.png",
            "header": "ความเป็นส่วนตัวและความปลอดภัยของข้อมูล",
            "content": "ไม่มีการถ่ายโอนข้อมูลไปยังเซิร์ฟเวอร์ของเราหรือใช้เพื่อวัตถุประสงค์ทางการตลาดใด ๆ ในขณะที่ใช้เครื่องมือขนาด 12x18กิจกรรมทั้งหมดดำเนินการในขณะที่ใช้ภาพ resizer เพื่อ 12x18 ขนาดเครื่องมือจะเสร็จสมบูรณ์ แต่เพียงผู้เดียวภายในเบราว์เซอร์ด้วยเหตุนี้เราจึงสามารถให้ความปลอดภัยสูงสุดแก่ลูกค้าของเราทั้งหมด ซึ่งทำให้ภาพของ resizer ของเราเป็นเครื่องมือขนาด 12x18 เชื่อถือได้และปลอดภัยอย่างสมบูรณ์ในการใช้งานในทุกสถานการณ์"
        },
        {
            "priority": 1,
            "logoUrl": "/img/featureproperty/free.png",
            "header": "สามารถใช้ได้กับทุกคนโดยไม่มีค่าใช้จ่าย",
            "content": "ทุกคนยินดีที่จะใช้ภาพ resizer เพื่อ 12x18 ขนาดเครื่องมือและไม่มีความต้องการในการลงทะเบียนการใช้เครื่องมือขนาด 12x18 ของเรซิเซอร์อิมเมจของเราเป็นบริการฟรีโดยสิ้นเชิง และเราจะไม่คิดค่าบริการอะไรจากคุณเมื่อใช้เครื่องมือ resizer image เพื่อ 12x18 มิติ, ไม่มีการ จำกัด จำนวนครั้งที่คุณสามารถปรับขนาดภาพของคุณ."
        },
        {
            "priority": 1,
            "logoUrl": "/img/featureproperty/userfriendly.png",
            "header": "ความสามารถในการปรับตัว",
            "content": "Chrome, Safari, Firefox, Microsoft Edge และเบราว์เซอร์ยอดนิยมอื่น ๆ ได้รับการสนับสนุนโดยภาพ resizer เพื่อ 12x18 เครื่องมือมิติเมื่อคุณใช้เครื่องมือขนาด 12x18 อิมเมจจะปรับให้เข้ากับขนาดหน้าจอใด ๆ ทำให้สามารถเข้าถึงได้ง่ายสำหรับคุณบนคอมพิวเตอร์เดสก์ท็อป คอมพิวเตอร์แท็บเล็ต หรือโทรศัพท์มือถือ"
        },
        {
            "priority": 1,
            "logoUrl": "/img/featureproperty/nodownload.png",
            "header": "ไม่จำเป็นต้องดาวน์โหลดเพิ่มเติม",
            "content": "เพื่อที่จะใช้เครื่องมือ resizer image ของเราเพื่อ 12x18 ขนาด, เราไม่จำเป็นต้องให้คุณดาวน์โหลดหรือติดตั้งซอฟต์แวร์ใด ๆ บนคอมพิวเตอร์หรืออุปกรณ์มือถือของคุณ.เครื่องมือ resizer image to 12x18 ของเราใช้เบราว์เซอร์อย่างเต็มรูปแบบ และคุณสามารถเข้าถึงเว็บไซต์ของเราได้ตลอดเวลาโดยเพียงแค่ป้อน URL ของเราลงในเบราว์เซอร์ของคุณและใช้เครื่องมือตามความจำเป็น"
        }
    ],
    "HOW_TO_CONTENT": {
        "logoImageUrl": "/idea.svg",
        "heading": "วิธีปรับขนาดภาพ",
        "steps": [
            "คลิกที่เลือกไฟล์เพื่ออัปโหลดภาพจากอุปกรณ์ของคุณ หรือคลิกที่ปุ่มแบบเลื่อนลงเพื่ออัปโหลดจาก Dropbox หรือ Google ไดรฟ์",
            "ปรับขนาดและรูปแบบของภาพตามข้อมูลจำเพาะที่คุณต้องการ",
            "หากต้องการดูการเปลี่ยนแปลงที่คุณทำ ให้คลิก แสดงตัวอย่าง",
            "บันทึกการเปลี่ยนแปลงของคุณโดยคลิกที่ปุ่มบันทึกการเปลี่ยนแปลง",
            "หากต้องการรับภาพที่มีการปรับขนาดให้คลิกปุ่มดาวน์โหลด"
        ]
    },

    "jscdns": [
        "<script src='/assets/js/googledrive.js'></script>",
        "<script src='https://cdnjs.cloudflare.com/ajax/libs/compressorjs/1.0.7/compressor.min.js' integrity='sha512-ZNlHFR9FBdeIlhwh018g5JmmYj7DQOwkqb9Y+DBJ1MaTzRMxKZkfHWkQU/dazDn9XRriajfh7ZGFksBKeUCsCg==' crossorigin='anonymous' referrerpolicy='no-referrer'></script>"
    ],
    "csscdns": [
        "<link rel='stylesheet' href='/css/utils.css' />",
        "<link rel='stylesheet' href='/css/image-resize.css' />"
    ]
}