{
    "Language": "한국어",
    "htmlLangAtt": "ko",
    "H1": "무료 온라인 2400x3000 치수 이미지 리사이 저 (픽셀 단위)",
    "keywords": "resize image to 2400x3000",
    "img": "/img/resize.png",
    "imgwidth": "35px",
    "imgheight": "35px",
    "imgalt": "altvalue",
    "nofileupload": true,
    "variant": "경고를 표시합니다",
    "H2": "이미지 크기를 2400x3000 치수로 빠르게 조정하는 데 가장 적합한 도구",
    "TITLE": "품질 저하없이 이미지 크기를 2400x3000 픽셀 단위로 조정 - 최고의 무료 온라인 도구",
    "META": "화질을 잃지 않고 즉시 2400x3000 비율로 이미지 크기를 조정하십시오.이 무료 크기 조정 이미지 (2400x3000) 도구를 사용하면 로그인 요구 사항없이 크기가 조정 된 이미지를 JPG, JPEG, PNG 및 WEBP 형식으로 다운로드 할 수 있습니다.",
    "LABEL": "",
    "BREADCRUMB_LABEL": "",
    "color": "#0D66D0",  
    "megaMenu": {
        "nav-link-name": "Tools",
        "dropdown": [
            {
                "categoryName": "이미지 리사이저 (인치)",
                "links": [
                    {
                        "name": "이미지를 3x5로 크기 조정 ",
                        "iconSrc": "/img/resize.png",
                        "url": "/ko/resize-image-to-3x5"
                    },
                    {
                        "name": "이미지를 4x6으로 크기 조정 ",
                        "iconSrc": "/img/resize.png",
                        "url": "/ko/resize-image-to-4x6"
                    },
                    {
                        "name": "이미지를 5x7로 크기 조정 ",
                        "iconSrc": "/img/resize.png",
                        "url": "/ko/resize-image-to-5x7"
                    },
                    {
                        "name": "이미지를 8x8로 크기 조정",
                        "iconSrc": "/img/resize.png",
                        "url": "/ko/resize-image-to-8x8"
                    },
                    {
                        "name": "이미지를 8x10으로 크기 조정 ",
                        "iconSrc": "/img/resize.png",
                        "url": "/ko/resize-image-to-8x10"
                    },
                    {
                        "name": "이미지를 8x11로 크기 조정 ",
                        "iconSrc": "/img/resize.png",
                        "url": "/ko/resize-image-to-8x11"
                    },
                    {
                        "name": "이미지를 2x2로 크기 조정 ",
                        "iconSrc": "/img/resize.png",
                        "url": "/ko/resize-image-to-2x2"
                    },
                    {
                        "name": "이미지를 9x16으로 크기 조정 ",
                        "iconSrc": "/img/resize.png",
                        "url": "/ko/resize-image-to-9x16"
                    },
                    {
                        "name": "이미지를 11x14로 크기 조정 ",
                        "iconSrc": "/img/resize.png",
                        "url": "/ko/resize-image-to-11x14"
                    },
                    {
                        "name": "이미지를 11x16으로 크기 조정 ",
                        "iconSrc": "/img/resize.png",
                        "url": "/ko/resize-image-to-11x16"
                    },
                    {
                        "name": "이미지를 12x18로 크기 조정 ",
                        "iconSrc": "/img/resize.png",
                        "url": "/ko/resize-image-to-12x18"
                    },
                    {
                        "name": "이미지를 18x24로 크기 조정 ",
                        "iconSrc": "/img/resize.png",
                        "url": "/ko/resize-image-to-18x24"
                    },
                    {
                        "name": "이미지를 18x36으로 크기 조정 ",
                        "iconSrc": "/img/resize.png",
                        "url": "/ko/resize-image-to-18x36"
                    },
                    {
                        "name": "이미지를 20x24로 크기 조정 ",
                        "iconSrc": "/img/resize.png",
                        "url": "/ko/resize-image-to-20x24"
                    },
                    {
                        "name": "이미지를 24x36으로 크기 조정 ",
                        "iconSrc": "/img/resize.png",
                        "url": "/ko/resize-image-to-24x36"
                    },
                    {
                        "name": "이미지를 24x30으로 크기 조정 ",
                        "iconSrc": "/img/resize.png",
                        "url": "/ko/resize-image-to-24x30"
                    },
                    {
                        "name": "이미지를 24x48로 크기 조정 ",
                        "iconSrc": "/img/resize.png",
                        "url": "/ko/resize-image-to-24x48"
                    },
                    {
                        "name": "이미지를 29x21로 크기 조정하기 ",
                        "iconSrc": "/img/resize.png",
                        "url": "/ko/resize-image-to-29x21"
                    },
                    {
                        "name": "이미지를 30x36으로 크기 조정 ",
                        "iconSrc": "/img/resize.png",
                        "url": "/ko/resize-image-to-30x36"
                    },
                    {
                        "name": "이미지를 30x40으로 크기 조정 ",
                        "iconSrc": "/img/resize.png",
                        "url": "/ko/resize-image-to-30x40"
                    }
                ]
            },
            {
                "categoryName": "이미지 리사이저 (픽셀)",
                "links": [
                    {
                        "name": "이미지를 900x1500으로 크기 조정하기 ",
                        "iconSrc": "/img/resize.png",
                        "url": "/ko/resize-image-to-900x1500"
                    },
                    {
                        "name": "이미지를 1200x1800으로 크기 조정하기 ",
                        "iconSrc": "/img/resize.png",
                        "url": "/ko/resize-image-to-1200x1800"
                    },
                    {
                        "name": "이미지를 32x32로 크기 조정 ",
                        "iconSrc": "/img/resize.png",
                        "url": "/ko/resize-image-to-32x32"
                    },
                    {
                        "name": "이미지를 42x59로 크기 조정 ",
                        "iconSrc": "/img/resize.png",
                        "url": "/ko/resize-image-to-42x59"
                    },
                    {
                        "name": "이미지를 128x128로 크기 조정하기 ",
                        "iconSrc": "/img/resize.png",
                        "url": "/ko/resize-image-to-128x128"
                    },
                    {
                        "name": "이미지를 21x29로 크기 조정 ",
                        "iconSrc": "/img/resize.png",
                        "url": "/ko/resize-image-to-21x29"
                    },
                    {
                        "name": "이미지를 150x150으로 크기 조정하기 ",
                        "iconSrc": "/img/resize.png",
                        "url": "/ko/resize-image-to-150x150"
                    },
                    {
                        "name": "이미지를 168x168로 크기 조정하기 ",
                        "iconSrc": "/img/resize.png",
                        "url": "/ko/resize-image-to-168x168"
                    },
                    {
                        "name": "이미지를 170x170으로 크기 조정하기 ",
                        "iconSrc": "/img/resize.png",
                        "url": "/ko/resize-image-to-170x170"
                    },
                    {
                        "name": "이미지를 254x94로 크기 조정하기 ",
                        "iconSrc": "/img/resize.png",
                        "url": "/ko/resize-image-to-254x94"
                    },
                    {
                        "name": "이미지를 266x177로 크기 조정하기 ",
                        "iconSrc": "/img/resize.png",
                        "url": "/ko/resize-image-to-266x177"
                    },
                    {
                        "name": "이미지를 300x300으로 크기 조정하기 ",
                        "iconSrc": "/img/resize.png",
                        "url": "/ko/resize-image-to-300x300"
                    },
                    {
                        "name": "이미지를 320x320으로 크기 조정하기 ",
                        "iconSrc": "/img/resize.png",
                        "url": "/ko/resize-image-to-320x320"
                    },
                    {
                        "name": "이미지를 385x256으로 크기 조정하기 ",
                        "iconSrc": "/img/resize.png",
                        "url": "/ko/resize-image-to-385x256"
                    },
                    {
                        "name": "이미지를 450x450으로 크기 조정하기 ",
                        "iconSrc": "/img/resize.png",
                        "url": "/ko/resize-image-to-450x450"
                    },
                    {
                        "name": "이미지를 500x500으로 크기 조정하기 ",
                        "iconSrc": "/img/resize.png",
                        "url": "/ko/resize-image-to-500x500"
                    },
                    {
                        "name": "이미지를 560x208로 크기 조정하기 ",
                        "iconSrc": "/img/resize.png",
                        "url": "/ko/resize-image-to-560x208"
                    },
                    {
                        "name": "이미지를 630x1200으로 크기 조정하기 ",
                        "iconSrc": "/img/resize.png",
                        "url": "/ko/resize-image-to-630x1200"
                    },
                    {
                        "name": "이미지를 700x800으로 크기 조정하기 ",
                        "iconSrc": "/img/resize.png",
                        "url": "/ko/resize-image-to-700x800"
                    },
                    {
                        "name": "이미지를 800x2000으로 크기 조정하기 ",
                        "iconSrc": "/img/resize.png",
                        "url": "/ko/resize-image-to-800x2000"
                    },
                    {
                        "name": "이미지를 900x1500으로 크기 조정하기 ",
                        "iconSrc": "/img/resize.png",
                        "url": "/ko/resize-image-to-900x1500"
                    },
                    {
                        "name": "이미지를 1000x524로 크기 조정하기 ",
                        "iconSrc": "/img/resize.png",
                        "url": "/ko/resize-image-to-1000x524"
                    },
                    {
                        "name": "이미지를 1000x1000으로 크기 조정하기 ",
                        "iconSrc": "/img/resize.png",
                        "url": "/ko/resize-image-to-1000x1000"
                    },
                    {
                        "name": "이미지를 1024x768로 크기 조정하기 ",
                        "iconSrc": "/img/resize.png",
                        "url": "/ko/resize-image-to-1024x768"
                    },
                    {
                        "name": "이미지를 1080x1920으로 크기 조정하기 ",
                        "iconSrc": "/img/resize.png",
                        "url": "/ko/resize-image-to-1080x1920"
                    },
                    {
                        "name": "이미지를 1080x1080으로 크기 조정하기 ",
                        "iconSrc": "/img/resize.png",
                        "url": "/ko/resize-image-to-1080x1080"
                    },
                    {
                        "name": "이미지를 1080x1350으로 크기 조정하기 ",
                        "iconSrc": "/img/resize.png",
                        "url": "/ko/resize-image-to-1080x1350"
                    },
                    {
                        "name": "이미지를 1200x628로 크기 조정하기 ",
                        "iconSrc": "/img/resize.png",
                        "url": "/ko/resize-image-to-1200x628"
                    },
                    {
                        "name": "이미지를 1200x630으로 크기 조정하기 ",
                        "iconSrc": "/img/resize.png",
                        "url": "/ko/resize-image-to-1200x630"
                    },
                    {
                        "name": "이미지를 1200x675로 크기 조정하기 ",
                        "iconSrc": "/img/resize.png",
                        "url": "/ko/resize-image-to-1200x675"
                    },
                    {
                        "name": "이미지를 1200x1200으로 크기 조정하기 ",
                        "iconSrc": "/img/resize.png",
                        "url": "/ko/resize-image-to-1200x1200"
                    },
                    {
                        "name": "이미지를 1200x1800으로 크기 조정하기 ",
                        "iconSrc": "/img/resize.png",
                        "url": "/ko/resize-image-to-1200x1800"
                    },
                    {
                        "name": "이미지를 1280x720으로 크기 조정하기 ",
                        "iconSrc": "/img/resize.png",
                        "url": "/ko/resize-image-to-1280x720"
                    },
                    {
                        "name": "이미지를 1500x2100으로 크기 조정하기 ",
                        "iconSrc": "/img/resize.png",
                        "url": "/ko/resize-image-to-1500x2100"
                    },
                    {
                        "name": "이미지를 1584x396으로 크기 조정하기 ",
                        "iconSrc": "/img/resize.png",
                        "url": "/ko/resize-image-to-1584x396"
                    },
                    {
                        "name": "이미지를 1640x923으로 크기 조정하기 ",
                        "iconSrc": "/img/resize.png",
                        "url": "/ko/resize-image-to-1640x923"
                    },
                    {
                        "name": "이미지를 1920x480으로 크기 조정하기 ",
                        "iconSrc": "/img/resize.png",
                        "url": "/ko/resize-image-to-1920x480"
                    },
                    {
                        "name": "이미지를 1920x1080으로 크기 조정하기 ",
                        "iconSrc": "/img/resize.png",
                        "url": "/ko/resize-image-to-1920x1080"
                    },
                    {
                        "name": "이미지를 1958x745로 크기 조정하기 ",
                        "iconSrc": "/img/resize.png",
                        "url": "/ko/resize-image-to-1958x745"
                    },
                    {
                        "name": "이미지를 2037x754로 크기 조정하기 ",
                        "iconSrc": "/img/resize.png",
                        "url": "/ko/resize-image-to-2037x754"
                    },
                    {
                        "name": "이미지를 2400x3000으로 크기 조정하기 ",
                        "iconSrc": "/img/resize.png",
                        "url": "/ko/resize-image-to-2400x3000"
                    },
                    {
                        "name": "이미지를 2550x3300으로 크기 조정하기 ",
                        "iconSrc": "/img/resize.png",
                        "url": "/ko/resize-image-to-2550x3300"
                    },
                    {
                        "name": "이미지를 2700x4800으로 크기 조정하기 ",
                        "iconSrc": "/img/resize.png",
                        "url": "/ko/resize-image-to-2700x4800"
                    },
                    {
                        "name": "이미지를 3300x4200으로 크기 조정하기 ",
                        "iconSrc": "/img/resize.png",
                        "url": "/ko/resize-image-to-3300x4200"
                    },
                    {
                        "name": "이미지를 3300x4800으로 크기 조정하기 ",
                        "iconSrc": "/img/resize.png",
                        "url": "/ko/resize-image-to-3300x4800"
                    }
                ]
            }
        ]
    },
    "TEXTUAL_CONTENT": [
        {
            "priority": 1,
            "logoUrl": "/img/featureproperty/highquality.png",
            "header": "고품질",
            "content": "크기 조정 이미지를 2400x3000 크기로 도구를 사용하면 화질을 잃지 않고 픽셀 단위로 이미지 크기를 조정할 수 있습니다.확장된 이미지는 원본 이미지와 동일한 종횡비를 가지므로 이미지를 자를 필요가 없습니다.기술적 요구 사항이 없기 때문에 기술자가 아닌 사람도 절차를 완료 할 수 있습니다.또한 크기가 조정된 이미지의 미리보기를 제공하므로 가능한 가장 효율적인 방법으로 크기 조정 절차를 완료 할 수 있습니다."
        },
        {
            "priority": 1,
            "logoUrl": "/img/featureproperty/security.png",
            "header": "사용하기 쉬움",
            "content": "이 크기 조정 이미지는 픽셀 단위의 2400x3000 치수 도구로 사용하기가 매우 쉽습니다.우선 사용자 인터페이스는 매우 단순하고 쉽습니다.모든 것이 한 곳에 있기 때문에 어디서 편집을 시작해야 할지 추측할 필요가 없습니다.또한 2400x3000 치수 도구에 대한 크기 조정 이미지에는 광고가 없으므로 최종 사용자에게 더 즐거운 사용자 경험을 제공합니다."
        },
        {
            "priority": 1,
            "logoUrl": "/img/featureproperty/flexible.png",
            "header": "데이터 개인 정보 보호 및 보안",
            "content": "크기 조정 이미지를 2400x3000 치수 도구로 사용하는 경우 어떠한 데이터도 당사 시스템에 업로드되거나 마케팅 목적으로 사용되지 않습니다.크기 조정 이미지를 2400x3000 치수 도구로 사용할 때 수행되는 모든 작업은 전적으로 브라우저 내에서 수행됩니다.결과적으로 우리는 모든 고객에게 완벽한 보안을 제공 할 수 있으므로 크기 조정 이미지를 2400x3000 치수 도구로 신뢰할 수 있고 어떤 상황에서도 위험 부담없이 사용할 수 있습니다."
        },
        {
            "priority": 1,
            "logoUrl": "/img/featureproperty/userfriendly.png",
            "header": "완전 무료",
            "content": "이미지를 2400x3000 크기로 변환하기 위해 이미지 크기 조정 도구를 사용하기 위해 등록하거나 로그인할 필요가 없습니다.크기 조정 이미지를 2400x3000 치수 도구로 사용하기 위해 비용을 지불하지 않아도됩니다.이미지 크기를 2400x3000 크기로 원하는 만큼 조정할 수 있습니다."
        },
        {
            "priority": 1,
            "logoUrl": "/img/featureproperty/free.png",
            "header": "적응성",
            "content": "크기 조정 이미지 2400x3000 크기 도구는 크롬, 사파리, 파이어폭스, 마이크로소프트 엣지 등 다양한 일반 브라우저와 호환됩니다.크기 조정 이미지 2400x3000 크기 도구를 사용하면 모든 화면 크기에 맞게 자동으로 조정되므로 기본 설정에 따라 데스크톱 컴퓨터, 태블릿 컴퓨터 또는 휴대폰에서 편리하게 액세스 할 수 있습니다."
        },
        {
            "priority": 1,
            "logoUrl": "/img/featureproperty/nodownload.png",
            "header": "다른 소프트웨어를 설치할 필요가 없습니다.",
            "content": "크기 조정 이미지 to 2400x3000 치수 도구를 사용하기 위해 컴퓨터 또는 모바일 장치에 소프트웨어를 다운로드하거나 설치할 필요가 없습니다.크기 조정 이미지 2400x3000 치수 도구는 완전히 웹 기반이므로 언제든지 사용할 수 있습니다.웹 사이트의 URL을 브라우저에 붙여넣고 필요에 따라 사용하기만 하면 됩니다."
        }
    ],
    "HOW_TO_CONTENT": {
        "logoImageUrl": "/idea.svg",
        "heading": "이미지 크기 조정 방법",
        "steps": [
            "파일 선택을 클릭하여 장치에서 이미지를 업로드하거나 드롭 다운 버튼을 클릭하여 Dropbox 또는 Google 드라이브에서 업로드합니다.",
            "원하는 사양에 따라 이미지의 크기와 형식을 조정합니다.",
            "변경한 내용을 보려면 미리 보기를 클릭합니다.",
            "변경 사항 저장 버튼을 클릭하여 변경 사항을 저장합니다.",
            "크기가 조정된 이미지를 얻으려면 다운로드 버튼을 클릭합니다."
        ]
    },
   
    "jscdns": [
        "<script src='/assets/js/googledrive.js'></script>",
        "<script src='https://cdnjs.cloudflare.com/ajax/libs/compressorjs/1.0.7/compressor.min.js' integrity='sha512-ZNlHFR9FBdeIlhwh040g5JmmYj7DQOwkqb9Y+DBJ1MaTzRMxKZkfHWkQU/dazDn9XRriajfh7ZGFksBKeUCsCg==' crossorigin='anonymous' referrerpolicy='no-referrer'></script>"
    ],
    "csscdns": [
        "<link rel='stylesheet' href='/css/utils.css' />",
        "<link rel='stylesheet' href='/css/image-resize.css' />"
    ]
}