{
    "Language": "العربية",
    "htmlLangAtt": "ar",
    "H1": "تغيير حجم الصورة عبر الإنترنت إلى أبعاد 6X4 ",
    "img": "/img/resize.png",
    "imgwidth": "35px",
    "imgheight": "35px",
    "imgalt": "altvalue",
    "nofileupload": true,
    "variant": "تحذير",
    "H2": "قم بتغيير حجم الصورة إلى 6X4 مثل المحترفين باستخدام هذه الأداة.",
    "TITLE": "تغيير حجم الصورة - أفضل أداة لتغيير حجم الصورة إلى 6X4 بسهولة.",
    "META": "قم بتغيير حجم الصورة إلى 6 X4 بالطريقة السهلة باستخدام هذه الأداة سهلة الاستخدام. أفضل أداة لتغيير حجم الصورة وفقًا لمتطلباتك. احصل على النتيجة المرجوة دون أي قيود. تقوم هذه الأداة السحرية بتغيير حجم الصورة إلى x بنقرات قليلة فقط. لا حاجة لتثبيت أي برنامج.",
    "LABEL": "",
    "BREADCRUMB_LABEL": "",
    "color": "#0D66D0",
    "megaMenu": {
        "nav-link-name": "Tools",
        "dropdown": [
            {
                "categoryName": "تغيير حجم الصور بالبوصة",
                "links": [
                    {
                        "name": "صورة تغيير الحجم إلى 3X5 ",
                        "iconSrc": "/img/resize.png",
                        "url": "/ar/resize-image-to-3X5"
                    },
                    {
                        "name": "صورة تغيير الحجم إلى 4X6 ",
                        "iconSrc": "/img/resize.png",
                        "url": "/ar/resize-image-to-4X6"
                    },
                    {
                        "name": "صورة تغيير الحجم إلى 5X7 ",
                        "iconSrc": "/img/resize.png",
                        "url": "/ar/resize-image-to-5X7"
                    },
                    {
                        "name": "صورة تغيير الحجم إلى 8X8",
                        "iconSrc": "/img/resize.png",
                        "url": "/ar/resize-image-to-8X8"
                    },
                    {
                        "name": "صورة تغيير الحجم إلى 8X10 ",
                        "iconSrc": "/img/resize.png",
                        "url": "/ar/resize-image-to-8X10"
                    },
                    {
                        "name": "صورة تغيير الحجم إلى 8X11 ",
                        "iconSrc": "/img/resize.png",
                        "url": "/ar/resize-image-to-8X11"
                    },
                    {
                        "name": "صورة تغيير الحجم إلى 2X2 ",
                        "iconSrc": "/img/resize.png",
                        "url": "/ar/resize-image-to-2X2"
                    },
                    {
                        "name": "صورة تغيير الحجم إلى 9X16 ",
                        "iconSrc": "/img/resize.png",
                        "url": "/ar/resize-image-to-9X16"
                    },
                    {
                        "name": "صورة تغيير الحجم إلى 11X14 ",
                        "iconSrc": "/img/resize.png",
                        "url": "/ar/resize-image-to-11X14"
                    },
                    {
                        "name": "صورة تغيير الحجم إلى 11X16 ",
                        "iconSrc": "/img/resize.png",
                        "url": "/ar/resize-image-to-11X16"
                    },
                    {
                        "name": "صورة تغيير الحجم إلى 12X18 ",
                        "iconSrc": "/img/resize.png",
                        "url": "/ar/resize-image-to-12X18"
                    },
                    {
                        "name": "صورة تغيير الحجم إلى 18X24 ",
                        "iconSrc": "/img/resize.png",
                        "url": "/ar/resize-image-to-18X24"
                    },
                    {
                        "name": "صورة تغيير الحجم إلى 18X36 ",
                        "iconSrc": "/img/resize.png",
                        "url": "/ar/resize-image-to-18X36"
                    },
                    {
                        "name": "صورة تغيير الحجم إلى 20X24 ",
                        "iconSrc": "/img/resize.png",
                        "url": "/ar/resize-image-to-20X24"
                    },
                    {
                        "name": "صورة تغيير الحجم إلى 24X36 ",
                        "iconSrc": "/img/resize.png",
                        "url": "/ar/resize-image-to-24X36"
                    },
                    {
                        "name": "صورة تغيير الحجم إلى 24X30 ",
                        "iconSrc": "/img/resize.png",
                        "url": "/ar/resize-image-to-24X30"
                    },
                    {
                        "name": "صورة تغيير الحجم إلى 24X48 ",
                        "iconSrc": "/img/resize.png",
                        "url": "/ar/resize-image-to-24X48"
                    },
                    {
                        "name": "صورة تغيير الحجم إلى 29X21 ",
                        "iconSrc": "/img/resize.png",
                        "url": "/ar/resize-image-to-29X21"
                    },
                    {
                        "name": "صورة تغيير الحجم إلى 30X36 ",
                        "iconSrc": "/img/resize.png",
                        "url": "/ar/resize-image-to-30X36"
                    },
                    {
                        "name": "صورة تغيير الحجم إلى 30X40 ",
                        "iconSrc": "/img/resize.png",
                        "url": "/ar/resize-image-to-30X40"
                    }
                ]
            },
            {
                "categoryName": "تغيير حجم الصور بالبكسل",
                "links": [
                    {
                        "name": "صورة تغيير الحجم إلى 900X1500 ",
                        "iconSrc": "/img/resize.png",
                        "url": "/ar/resize-image-to-900X1500"
                    },
                    {
                        "name": "صورة تغيير الحجم إلى 1200X1800 ",
                        "iconSrc": "/img/resize.png",
                        "url": "/ar/resize-image-to-1200X1800"
                    },
                    {
                        "name": "صورة تغيير الحجم إلى 32X32 ",
                        "iconSrc": "/img/resize.png",
                        "url": "/ar/resize-image-to-32X32"
                    },
                    {
                        "name": "صورة تغيير الحجم إلى 42X59 ",
                        "iconSrc": "/img/resize.png",
                        "url": "/ar/resize-image-to-42X59"
                    },
                    {
                        "name": "صورة تغيير الحجم إلى 128X128 ",
                        "iconSrc": "/img/resize.png",
                        "url": "/ar/resize-image-to-128X128"
                    },
                    {
                        "name": "صورة تغيير الحجم إلى 21X29 ",
                        "iconSrc": "/img/resize.png",
                        "url": "/ar/resize-image-to-21X29"
                    },
                    {
                        "name": "صورة تغيير الحجم إلى 150X150 ",
                        "iconSrc": "/img/resize.png",
                        "url": "/ar/resize-image-to-150X150"
                    },
                    {
                        "name": "صورة تغيير الحجم إلى 168X168 ",
                        "iconSrc": "/img/resize.png",
                        "url": "/ar/resize-image-to-168X168"
                    },
                    {
                        "name": "صورة تغيير الحجم إلى 170X170 ",
                        "iconSrc": "/img/resize.png",
                        "url": "/ar/resize-image-to-170X170"
                    },
                    {
                        "name": "صورة تغيير الحجم إلى 254X94 ",
                        "iconSrc": "/img/resize.png",
                        "url": "/ar/resize-image-to-254X94"
                    },
                    {
                        "name": "صورة تغيير الحجم إلى 266X177 ",
                        "iconSrc": "/img/resize.png",
                        "url": "/ar/resize-image-to-266X177"
                    },
                    {
                        "name": "صورة تغيير الحجم إلى 300X300 ",
                        "iconSrc": "/img/resize.png",
                        "url": "/ar/resize-image-to-300X300"
                    },
                    {
                        "name": "صورة تغيير الحجم إلى 320X320 ",
                        "iconSrc": "/img/resize.png",
                        "url": "/ar/resize-image-to-320X320"
                    },
                    {
                        "name": "صورة تغيير الحجم إلى 385X256 ",
                        "iconSrc": "/img/resize.png",
                        "url": "/ar/resize-image-to-385X256"
                    },
                    {
                        "name": "صورة تغيير الحجم إلى 450X450 ",
                        "iconSrc": "/img/resize.png",
                        "url": "/ar/resize-image-to-450X450"
                    },
                    {
                        "name": "صورة تغيير الحجم إلى 500X500 ",
                        "iconSrc": "/img/resize.png",
                        "url": "/ar/resize-image-to-500X500"
                    },
                    {
                        "name": "صورة تغيير الحجم إلى 560X208 ",
                        "iconSrc": "/img/resize.png",
                        "url": "/ar/resize-image-to-560X208"
                    },
                    {
                        "name": "صورة تغيير الحجم إلى 630X1200 ",
                        "iconSrc": "/img/resize.png",
                        "url": "/ar/resize-image-to-630X1200"
                    },
                    {
                        "name": "صورة تغيير الحجم إلى 700X800 ",
                        "iconSrc": "/img/resize.png",
                        "url": "/ar/resize-image-to-700X800"
                    },
                    {
                        "name": "صورة تغيير الحجم إلى 800X2000 ",
                        "iconSrc": "/img/resize.png",
                        "url": "/ar/resize-image-to-800X2000"
                    },
                    {
                        "name": "صورة تغيير الحجم إلى 900X1500 ",
                        "iconSrc": "/img/resize.png",
                        "url": "/ar/resize-image-to-900X1500"
                    },
                    {
                        "name": "صورة تغيير الحجم إلى 1000X524 ",
                        "iconSrc": "/img/resize.png",
                        "url": "/ar/resize-image-to-1000X524"
                    },
                    {
                        "name": "صورة تغيير الحجم إلى 1000X1000 ",
                        "iconSrc": "/img/resize.png",
                        "url": "/ar/resize-image-to-1000X1000"
                    },
                    {
                        "name": "صورة تغيير الحجم إلى 1024X768 ",
                        "iconSrc": "/img/resize.png",
                        "url": "/ar/resize-image-to-1024X768"
                    },
                    {
                        "name": "صورة تغيير الحجم إلى 1080X1920 ",
                        "iconSrc": "/img/resize.png",
                        "url": "/ar/resize-image-to-1080X1920"
                    },
                    {
                        "name": "صورة تغيير الحجم إلى 1080X1080 ",
                        "iconSrc": "/img/resize.png",
                        "url": "/ar/resize-image-to-1080X1080"
                    },
                    {
                        "name": "صورة تغيير الحجم إلى 1080X1350 ",
                        "iconSrc": "/img/resize.png",
                        "url": "/ar/resize-image-to-1080X1350"
                    },
                    {
                        "name": "صورة تغيير الحجم إلى 1200X628 ",
                        "iconSrc": "/img/resize.png",
                        "url": "/ar/resize-image-to-1200X628"
                    },
                    {
                        "name": "صورة تغيير الحجم إلى 1200X630 ",
                        "iconSrc": "/img/resize.png",
                        "url": "/ar/resize-image-to-1200X630"
                    },
                    {
                        "name": "صورة تغيير الحجم إلى 1200X675 ",
                        "iconSrc": "/img/resize.png",
                        "url": "/ar/resize-image-to-1200X675"
                    },
                    {
                        "name": "صورة تغيير الحجم إلى 1200X1200 ",
                        "iconSrc": "/img/resize.png",
                        "url": "/ar/resize-image-to-1200X1200"
                    },
                    {
                        "name": "صورة تغيير الحجم إلى 1200X1800 ",
                        "iconSrc": "/img/resize.png",
                        "url": "/ar/resize-image-to-1200X1800"
                    },
                    {
                        "name": "صورة تغيير الحجم إلى 1280X720 ",
                        "iconSrc": "/img/resize.png",
                        "url": "/ar/resize-image-to-1280X720"
                    },
                    {
                        "name": "صورة تغيير الحجم إلى 1500X2100 ",
                        "iconSrc": "/img/resize.png",
                        "url": "/ar/resize-image-to-1500X2100"
                    },
                    {
                        "name": "صورة تغيير الحجم إلى 1584X396 ",
                        "iconSrc": "/img/resize.png",
                        "url": "/ar/resize-image-to-1584X396"
                    },
                    {
                        "name": "صورة تغيير الحجم إلى 1640X923 ",
                        "iconSrc": "/img/resize.png",
                        "url": "/ar/resize-image-to-1640X923"
                    },
                    {
                        "name": "صورة تغيير الحجم إلى 1920X480 ",
                        "iconSrc": "/img/resize.png",
                        "url": "/ar/resize-image-to-1920X480"
                    },
                    {
                        "name": "صورة تغيير الحجم إلى 1920X1080 ",
                        "iconSrc": "/img/resize.png",
                        "url": "/ar/resize-image-to-1920X1080"
                    },
                    {
                        "name": "صورة تغيير الحجم إلى 1958X745 ",
                        "iconSrc": "/img/resize.png",
                        "url": "/ar/resize-image-to-1958X745"
                    },
                    {
                        "name": "صورة تغيير الحجم إلى 2037X754 ",
                        "iconSrc": "/img/resize.png",
                        "url": "/ar/resize-image-to-2037X754"
                    },
                    {
                        "name": "صورة تغيير الحجم إلى 2400X3000 ",
                        "iconSrc": "/img/resize.png",
                        "url": "/ar/resize-image-to-2400X3000"
                    },
                    {
                        "name": "صورة تغيير الحجم إلى 2550X3300 ",
                        "iconSrc": "/img/resize.png",
                        "url": "/ar/resize-image-to-2550X3300"
                    },
                    {
                        "name": "صورة تغيير الحجم إلى 2700X4800 ",
                        "iconSrc": "/img/resize.png",
                        "url": "/ar/resize-image-to-2700X4800"
                    },
                    {
                        "name": "صورة تغيير الحجم إلى 3300X4200 ",
                        "iconSrc": "/img/resize.png",
                        "url": "/ar/resize-image-to-3300X4200"
                    },
                    {
                        "name": "صورة تغيير الحجم إلى 3300X4800 ",
                        "iconSrc": "/img/resize.png",
                        "url": "/ar/resize-image-to-3300X4800"
                    }
                ]
            }
        ]
    },
    "TEXTUAL_CONTENT": [
        {
            "priority": 1,
            "logoUrl": "/img/featureproperty/highquality.png",
            "header": "حافظ على جودة الصورة عالية",
            "content": "من الممكن تغيير حجم الصور بالبوصة دون المساس بجودتها بمساعدة صورة تغيير الحجم الخاصة بنا إلى أداة أبعاد 6 × 4. ستكون نسبة العرض إلى الارتفاع للصورة المكبرة هي نفس نسبة الصورة الأصلية. لا توجد متطلبات تكنولوجية، وحتى المستخدمين غير التقنيين يمكنهم إكمال الإجراء. كما يوفر لك معاينة للصورة التي تم تغيير حجمها، مما يسمح لك بإكمال إجراء تغيير الحجم بأكثر الطرق سلاسة ممكنة."
        },
        {
            "priority": 1,
            "logoUrl": "/img/featureproperty/security.png",
            "header": "سهل الاستخدام",
            "content": "أداة أبعاد أداة تغيير حجم الصورة 6X4 بالبوصة سهلة التشغيل للغاية. أولاً وقبل كل شيء، واجهة المستخدم بسيطة ومباشرة حقًا. نظرًا لحقيقة أن كل شيء في مكان واحد، لن تضطر إلى تخمين مكان بدء التحرير. بالإضافة إلى ذلك، لا تحتوي أداة تغيير الحجم الخاصة بنا إلى أداة الأبعاد 6X4 على أي إعلانات، مما يؤدي إلى تجربة مستخدم أكثر متعة للمستخدم النهائي."
        },
        {
            "priority": 1,
            "logoUrl": "/img/featureproperty/flexible.png",
            "header": "الخصوصية وأمن البيانات",
            "content": "لا يتم نقل أي بيانات إلى خوادمنا أو استخدامها لأي أغراض تسويقية أثناء استخدام صورة تغيير الحجم إلى أداة الأبعاد 6X4. يتم إكمال جميع الأنشطة التي يتم تنفيذها أثناء استخدام صورة تغيير الحجم لأداة الأبعاد 6X4 فقط داخل المتصفح. ونتيجة لذلك، نحن قادرون على توفير السلامة الكاملة لجميع عملائنا، مما يجعل صورة تغيير الحجم لدينا إلى أداة أبعاد 6X4 يمكن الاعتماد عليها وآمنة تمامًا للاستخدام في أي موقف."
        },
        {
            "priority": 1,
            "logoUrl": "/img/featureproperty/userfriendly.png",
            "header": "إنه متاح للجميع دون أي تكلفة",
            "content": "الجميع مدعوون لاستخدام صورة تغيير الحجم لأداة الأبعاد 6X4، وليس هناك شرط للتسجيل. استخدام صورة تغيير الحجم الخاصة بنا لأداة الأبعاد 6X4 مجاني تمامًا، ونحن لا نفرض عليك أي رسوم مقابل ذلك. عند استخدام صورة تغيير الحجم لأداة الأبعاد 6X4، لا يوجد حد لعدد المرات التي يمكنك فيها تغيير حجم صورك."
        },
        {
            "priority": 1,
            "logoUrl": "/img/featureproperty/free.png",
            "header": "القدرة على التكيف",
            "content": "يتم دعم كل من Chrome و Safari و Firefox و Microsoft Edge والمتصفحات الشائعة الأخرى بواسطة صورة تغيير الحجم إلى أداة الأبعاد 6X4. عند استخدام صورة تغيير الحجم لأداة الأبعاد 6×4، فسوف تتكيف مع أي حجم للشاشة، مما يجعلها سهلة الوصول لك على جهاز الكمبيوتر المكتبي أو الكمبيوتر اللوحي أو الهاتف المحمول."
        },
        {
            "priority": 1,
            "logoUrl": "/img/featureproperty/nodownload.png",
            "header": "لا يوجد تنزيل إضافي مطلوب",
            "content": "من أجل استخدام صورة تغيير الحجم الخاصة بنا لأداة الأبعاد 6X4، لا نطلب منك تنزيل أو تثبيت أي برنامج على جهاز الكمبيوتر أو الجهاز المحمول. إن أداة تغيير الحجم الخاصة بنا إلى أبعاد 6×4 تعتمد بالكامل على المتصفح، ويمكنك الوصول إلى موقعنا في أي وقت بمجرد إدخال عنوان URL الخاص بنا في متصفحك واستخدام الأداة حسب الحاجة."
        }
    ],
    "HOW_TO_CONTENT": {
        "logoImageUrl": "/idea.svg",
        "heading": "كيفية تغيير حجم الصورة",
        "steps": [
            "قم بتحميل الصورة أو انقر فوق السهم المنسدل وحدد Dropbox/Google Drive لتحديد ملفك في المساحة المتوفرة.",
            "اضبط المعلمات للحصول على جودة صورة أفضل.\n",
            "اضغط على «معاينة» لإلقاء نظرة على التغييرات التي تم إجراؤها.",
            "احفظ التغييرات التي تم إجراؤها.",
            "مرحى!! الصورة جاهزة للاستخدام."
        ]
    },
    "FAQ": [
        {
            "question": "Is it safe to allow access to my drive?",
            "answer": "Yes, it is absolutely safe to allow and give us access to your drive. We won't be making any changes to your site and your dfiles will be safe with you."
        },
        {
            "question": "How can I upload files from my drive/dropbox?",
            "answer": "Click on the drop down arrow and select Dropbox/Google Drive. Select the Google account from where you want to link your drive. Now you can select the files that you want to upload."
        },
        {
            "question": "What are the features offered by resize image feature from safeimagekit.com while, adjusting the size of the images?",
            "answer": "Resize image offers versatile features from safeimagekit.com while sizing an image uploaded for editing. The main features include-\n-\tAdjusting the size of an image with respect to the width.\n-\tAdjusting the size of an image with respect to the height.\n-\tComplete resizing of the image and downloading them."
        },
        {
            "question": "How can I adjust the width of the image using the resize image feature from safeimagekit.com?",
            "answer": "The first step of all, upload the image which requires an edit. The next step includes adjusting the important parameters of the image, this includes adjusting the width and the height. The width of the image can be accessed by entering a value on the space called “enter the width”. The value of the width can be increased by entering the values which are positive (+) in nature. The value of the width can be decreased by entering the values which are negative (-) in nature."
        },
        {
            "question": "How can I adjust the height of the image using the resize image feature from safeimagekit.com?",
            "answer": "The first step of all, upload the image which requires an edit. The next step includes adjusting the important parameters of the image, this includes adjusting the width and the height. The height of the image can be accessed by entering a value on the space called “enter the height”. The value of the height can be increased by entering the values which are positive (+) in nature. The value of the width can be decreased by entering the values which are negative (-) in nature."
        },
        {
            "question": "How can I resize an image using the resize image feature from safeimagekit.com?",
            "answer": "There are 6 steps that the user can refer to while resizing an image file,\nThese include-\n-\tUpload the image file which requires a change.\n-\tAdjust the height of the image by entering a value.\n-\tAdjust the width of the image by entering a value.\n-\tHit the resize button to activate the resize.\n-\tHit the save button to save the changes made.\n-\tUse the download option to download the modified image."
        },
        {
            "question": "Does the resize option of resize image feature from safeimagekit.com provide any type of preview after resizing the uploaded image file?",
            "answer": "No, currently the resizing feature of photo splitter from safeimagekit.com does not provide any kind of preview of the sections of the uploaded image, because sometimes the sections of the uploaded image go overboard and it becomes very difficult for the browser to handle the preview of each and every section of the image. However, updates to the website in the future will add all the exciting features."
        },
        {
            "question": "Can I use the resize image feature from safeimagekit.com on my Windows 8?",
            "answer": "Resize image feature is a versatile feature offered by safeimagekit.com which is supported by all the operating systems out there such as Windows 8, Linux, and even Ubuntu. All it takes is a device to open the extension file using the www.safeimagekit.com website and a normal internet connection to stand on. The fun fact is that it can even run on a slower internet connection."
        },
        {
            "question": "Can I use the resize image feature from safeimagekit.com on my Android device? ",
            "answer": "Yes, resize image feature from safeimagekit.com is a cross-platform based feature where the user can use this converter tool from operating systems such as Android, iOS, Windows, and Mac OS. It is independent of the operating systems used but only depends on the internet connection."
        },
        {
            "question": "Do we have to use any additional software to download the modified images after conversion using the resize image feature from safeimagekit.com?",
            "answer": "No, the users after resizing their image by entering their respective height and width, can hit the download the option which is given below and can download the modified image. It is a browser-based converter tool that does not support or no additional software is required to download the modified image."
        },
        {
            "question": "What will happen to our progress if we refresh our browser while we are using the resize image tool from safeimagekit.com?",
            "answer": "The resize image tool from safeimagekit.com is not connected to any server out there, so the data which the user is working on will not be stored anywhere and as a result, it will be erased instantly when the user refreshes the browser which he is working on. The image file which is being converted will also be removed after the user exits or closes the tab on which the extension page of the website is open."
        },
        {
            "question": "Can we resize the image files which are locked, using the resize image feature from safeimagekit.com?",
            "answer": "No, we cannot upload the image file which is locked as the access to that particular image file is blocked. So, to use the resize image feature from safeimagekit.com we need to upload the image files which are not locked. But the user can check the password finder extension from safeimagekit.com which is exclusively made for unlocking image as well as image files in case the user loses his password for his locked image file."
        },
        {
            "question": "Will my uploaded image files corrupt after resizing the image files using the image resizer file feature from safeimagekit.com?",
            "answer": "No, safeimagekit.com is built with all the latest programs and security features which does not allow the uploaded image files to corrupt. So, the uploaded image files are completely safe and secured."
        },
        {
            "question": "Will my file be saved after I complete working on the image resizer tool? ",
            "answer": "No, we do not send any of your files to our servers all the operations are done on the browser itself therefore all your files are completely safe. "
        },
        {
            "question": "Do I have to do any additional signup or pay extra to use the image resizer tool? ",
            "answer": "Absolutely not, our tool is completely online and does not require you to share any of your personal information with us, like email id, passwords etc. Our tool is completely free of cost."
        },
        {
            "question": "How do I communicate if I face any issues or if I want to give any suggestions?",
            "answer": "We gladly take in any issue or suggestions offered by all the users, please contact us through our social media handles for more information. Safeimagekit.com is available on all the leading social media websites such as Facebook, Instagram, YouTube, and LinkedIn, etc."
        }
    ],
    "jscdns": [
        "<script src=\"/assets/js/googledrive.js\"></script>",
        "<script src='https://cdnjs.cloudflare.com/ajax/libs/compressorjs/1.0.7/compressor.min.js' integrity='sha512-ZNlHFR9FBdeIlhwh040g5JmmYj7DQOwkqb9Y+DBJ1MaTzRMxKZkfHWkQU/dazDn9XRriajfh7ZGFksBKeUCsCg==' crossorigin='anonymous' referrerpolicy='no-referrer'></script>"
    ],
    "csscdns": [
        "<link rel=\"stylesheet\" href=\"/css/utils.css\" />",
        "<link rel=\"stylesheet\" href=\"/css/image-resize.css\" />"
    ]
}