{
    "Language": "العربية",
    "htmlLangAtt": "ar",
    "H1": "تغيير حجم الصورة عبر الإنترنت إلى أبعاد 5X8 ",
    "img": "/img/resize.png",
    "imgwidth": "35px",
    "imgheight": "35px",
    "imgalt": "altvalue",
    "nofileupload": true,
    "variant": "تحذير",
    "H2": "قم بتغيير حجم الصورة إلى 5X8 مثل المحترفين باستخدام هذه الأداة.",
    "TITLE": "تغيير حجم الصورة - أفضل أداة لتغيير حجم الصورة إلى 5X8 بسهولة.",
    "META": "قم بتغيير حجم الصورة إلى 5X8 بالطريقة السهلة باستخدام هذه الأداة سهلة الاستخدام. أفضل أداة لتغيير حجم الصورة وفقًا لمتطلباتك. احصل على النتيجة المرجوة دون أي قيود. تقوم هذه الأداة السحرية بتغيير حجم الصورة إلى x بنقرات قليلة فقط. لا حاجة لتثبيت أي برنامج.",
    "LABEL": "",
    "BREADCRUMB_LABEL": "",
    "color": "#0D66D0",
    "megaMenu": {
        "nav-link-name": "Tools",
        "dropdown":[
            {
                "categoryName": "مغيرات الصور بالبوصة",
                "links": [
                    {
                        "name": "صورة تغيير الحجم إلى 3x5 ",
                        "iconSrc": "/img/resize.png",
                        "url": "/ar/resize-image-to-3x5"
                    },
                    {
                        "name": "صورة تغيير الحجم إلى 4x6 ",
                        "iconSrc": "/img/resize.png",
                        "url": "/ar/resize-image-to-4x6"
                    },
                    {
                        "name": "صورة تغيير الحجم إلى 5x7 ",
                        "iconSrc": "/img/resize.png",
                        "url": "/ar/resize-image-to-5x7"
                    },
                    {
                        "name": "صورة تغيير حجم إلى 8x8",
                        "iconSrc": "/img/resize.png",
                        "url": "/ar/resize-image-to-8x8"
                    },
                    {
                        "name": "صورة تغيير الحجم إلى 8x10 ",
                        "iconSrc": "/img/resize.png",
                        "url": "/ar/resize-image-to-8x10"
                    },
                    {
                        "name": "صورة تغيير حجم إلى 8x11 ",
                        "iconSrc": "/img/resize.png",
                        "url": "/ar/resize-image-to-8x11"
                    },
                    {
                        "name": "صورة تغيير الحجم إلى 2x2 ",
                        "iconSrc": "/img/resize.png",
                        "url": "/ar/resize-image-to-2x2"
                    },
                    {
                        "name": "صورة تغيير الحجم إلى 9x16 ",
                        "iconSrc": "/img/resize.png",
                        "url": "/ar/resize-image-to-9x16"
                    },
                    {
                        "name": "صورة تغيير الحجم إلى 11x14 ",
                        "iconSrc": "/img/resize.png",
                        "url": "/ar/resize-image-to-11x14"
                    },
                    {
                        "name": "صورة تغيير الحجم إلى 11x16 ",
                        "iconSrc": "/img/resize.png",
                        "url": "/ar/resize-image-to-11x16"
                    },
                    {
                        "name": "صورة تغيير الحجم إلى 12x18 ",
                        "iconSrc": "/img/resize.png",
                        "url": "/ar/resize-image-to-12x18"
                    },
                    {
                        "name": "صورة تغيير الحجم إلى 18x24 ",
                        "iconSrc": "/img/resize.png",
                        "url": "/ar/resize-image-to-18x24"
                    },
                    {
                        "name": "صورة تغيير الحجم إلى 18x36 ",
                        "iconSrc": "/img/resize.png",
                        "url": "/ar/resize-image-to-18x36"
                    },
                    {
                        "name": "صورة تغيير الحجم إلى 20x24 ",
                        "iconSrc": "/img/resize.png",
                        "url": "/ar/resize-image-to-20x24"
                    },
                    {
                        "name": "صورة تغيير الحجم إلى 24x36 ",
                        "iconSrc": "/img/resize.png",
                        "url": "/ar/resize-image-to-24x36"
                    },
                    {
                        "name": "صورة تغيير الحجم إلى 24x30 ",
                        "iconSrc": "/img/resize.png",
                        "url": "/ar/resize-image-to-24x30"
                    },
                    {
                        "name": "صورة تغيير الحجم إلى 24x48 ",
                        "iconSrc": "/img/resize.png",
                        "url": "/ar/resize-image-to-24x48"
                    },
                    {
                        "name": "صورة تغيير الحجم إلى 29x21 ",
                        "iconSrc": "/img/resize.png",
                        "url": "/ar/resize-image-to-29x21"
                    },
                    {
                        "name": "صورة تغيير الحجم إلى 30x36 ",
                        "iconSrc": "/img/resize.png",
                        "url": "/ar/resize-image-to-30x36"
                    },
                    {
                        "name": "صورة تغيير الحجم إلى 30x40 ",
                        "iconSrc": "/img/resize.png",
                        "url": "/ar/resize-image-to-30x40"
                    }
                ]
            },
            {
                "categoryName": "مغيرات الصور بالبكسل",
                "links": [
                    {
                        "name": "صورة تغيير الحجم إلى 900x1500 ",
                        "iconSrc": "/img/resize.png",
                        "url": "/ar/resize-image-to-900x1500"
                    },
                    {
                        "name": "صورة تغيير الحجم إلى 1200x1800 ",
                        "iconSrc": "/img/resize.png",
                        "url": "/ar/resize-image-to-1200x1800"
                    },
                    {
                        "name": "صورة تغيير الحجم إلى 32x32 ",
                        "iconSrc": "/img/resize.png",
                        "url": "/ar/resize-image-to-32x32"
                    },
                    {
                        "name": "صورة تغيير الحجم إلى 42x59 ",
                        "iconSrc": "/img/resize.png",
                        "url": "/ar/resize-image-to-42x59"
                    },
                    {
                        "name": "صورة تغيير حجم إلى 128x128 ",
                        "iconSrc": "/img/resize.png",
                        "url": "/ar/resize-image-to-128x128"
                    },
                    {
                        "name": "صورة تغيير الحجم إلى 21x29 ",
                        "iconSrc": "/img/resize.png",
                        "url": "/ar/resize-image-to-21x29"
                    },
                    {
                        "name": "صورة تغيير الحجم إلى 150x150 ",
                        "iconSrc": "/img/resize.png",
                        "url": "/ar/resize-image-to-150x150"
                    },
                    {
                        "name": "صورة تغيير الحجم إلى 168x168 ",
                        "iconSrc": "/img/resize.png",
                        "url": "/ar/resize-image-to-168x168"
                    },
                    {
                        "name": "صورة تغيير الحجم إلى 170x170 ",
                        "iconSrc": "/img/resize.png",
                        "url": "/ar/resize-image-to-170x170"
                    },
                    {
                        "name": "صورة تغيير الحجم إلى 254x94 ",
                        "iconSrc": "/img/resize.png",
                        "url": "/ar/resize-image-to-254x94"
                    },
                    {
                        "name": "صورة تغيير الحجم إلى 266x177 ",
                        "iconSrc": "/img/resize.png",
                        "url": "/ar/resize-image-to-266x177"
                    },
                    {
                        "name": "صورة تغيير الحجم إلى 300x300 ",
                        "iconSrc": "/img/resize.png",
                        "url": "/ar/resize-image-to-300x300"
                    },
                    {
                        "name": "صورة تغيير الحجم إلى 320x320 ",
                        "iconSrc": "/img/resize.png",
                        "url": "/ar/resize-image-to-320x320"
                    },
                    {
                        "name": "صورة تغيير الحجم إلى 385x256 ",
                        "iconSrc": "/img/resize.png",
                        "url": "/ar/resize-image-to-385x256"
                    },
                    {
                        "name": "صورة تغيير حجم إلى 450x450 ",
                        "iconSrc": "/img/resize.png",
                        "url": "/ar/resize-image-to-450x450"
                    },
                    {
                        "name": "صورة تغيير الحجم إلى 500x500 ",
                        "iconSrc": "/img/resize.png",
                        "url": "/ar/resize-image-to-500x500"
                    },
                    {
                        "name": "صورة تغيير الحجم إلى 560x208 ",
                        "iconSrc": "/img/resize.png",
                        "url": "/ar/resize-image-to-560x208"
                    },
                    {
                        "name": "صورة تغيير الحجم إلى 630x1200 ",
                        "iconSrc": "/img/resize.png",
                        "url": "/ar/resize-image-to-630x1200"
                    },
                    {
                        "name": "صورة تغيير الحجم إلى 700x800 ",
                        "iconSrc": "/img/resize.png",
                        "url": "/ar/resize-image-to-700x800"
                    },
                    {
                        "name": "صورة تغيير الحجم إلى 800x2000 ",
                        "iconSrc": "/img/resize.png",
                        "url": "/ar/resize-image-to-800x2000"
                    },
                    {
                        "name": "صورة تغيير الحجم إلى 900x1500 ",
                        "iconSrc": "/img/resize.png",
                        "url": "/ar/resize-image-to-900x1500"
                    },
                    {
                        "name": "صورة تغيير الحجم إلى 1000x524 ",
                        "iconSrc": "/img/resize.png",
                        "url": "/ar/resize-image-to-1000x524"
                    },
                    {
                        "name": "صورة تغيير الحجم إلى 1000x1000 ",
                        "iconSrc": "/img/resize.png",
                        "url": "/ar/resize-image-to-1000x1000"
                    },
                    {
                        "name": "صورة تغيير الحجم إلى 1024x768 ",
                        "iconSrc": "/img/resize.png",
                        "url": "/ar/resize-image-to-1024x768"
                    },
                    {
                        "name": "صورة تغيير الحجم إلى 1080x1920 ",
                        "iconSrc": "/img/resize.png",
                        "url": "/ar/resize-image-to-1080x1920"
                    },
                    {
                        "name": "صورة تغيير الحجم إلى 1080x1080 ",
                        "iconSrc": "/img/resize.png",
                        "url": "/ar/resize-image-to-1080x1080"
                    },
                    {
                        "name": "صورة تغيير الحجم إلى 1080x1350 ",
                        "iconSrc": "/img/resize.png",
                        "url": "/ar/resize-image-to-1080x1350"
                    },
                    {
                        "name": "صورة تغيير الحجم إلى 1200x628 ",
                        "iconSrc": "/img/resize.png",
                        "url": "/ar/resize-image-to-1200x628"
                    },
                    {
                        "name": "صورة تغيير الحجم إلى 1200x630 ",
                        "iconSrc": "/img/resize.png",
                        "url": "/ar/resize-image-to-1200x630"
                    },
                    {
                        "name": "صورة تغيير الحجم إلى 1200x675 ",
                        "iconSrc": "/img/resize.png",
                        "url": "/ar/resize-image-to-1200x675"
                    },
                    {
                        "name": "صورة تغيير الحجم إلى 1200x1200 ",
                        "iconSrc": "/img/resize.png",
                        "url": "/ar/resize-image-to-1200x1200"
                    },
                    {
                        "name": "صورة تغيير الحجم إلى 1200x1800 ",
                        "iconSrc": "/img/resize.png",
                        "url": "/ar/resize-image-to-1200x1800"
                    },
                    {
                        "name": "صورة تغيير الحجم إلى 1280x720 ",
                        "iconSrc": "/img/resize.png",
                        "url": "/ar/resize-image-to-1280x720"
                    },
                    {
                        "name": "صورة تغيير الحجم إلى 1500x2100 ",
                        "iconSrc": "/img/resize.png",
                        "url": "/ar/resize-image-to-1500x2100"
                    },
                    {
                        "name": "صورة تغيير الحجم إلى 1584x396 ",
                        "iconSrc": "/img/resize.png",
                        "url": "/ar/resize-image-to-1584x396"
                    },
                    {
                        "name": "صورة تغيير الحجم إلى 1640x923 ",
                        "iconSrc": "/img/resize.png",
                        "url": "/ar/resize-image-to-1640x923"
                    },
                    {
                        "name": "صورة تغيير الحجم إلى 1920x480 ",
                        "iconSrc": "/img/resize.png",
                        "url": "/ar/resize-image-to-1920x480"
                    },
                    {
                        "name": "صورة تغيير الحجم إلى 1920x1080 ",
                        "iconSrc": "/img/resize.png",
                        "url": "/ar/resize-image-to-1920x1080"
                    },
                    {
                        "name": "صورة تغيير الحجم إلى 1958x745 ",
                        "iconSrc": "/img/resize.png",
                        "url": "/ar/resize-image-to-1958x745"
                    },
                    {
                        "name": "صورة تغيير الحجم إلى 2037x754 ",
                        "iconSrc": "/img/resize.png",
                        "url": "/ar/resize-image-to-2037x754"
                    },
                    {
                        "name": "صورة تغيير الحجم إلى 2400x3000 ",
                        "iconSrc": "/img/resize.png",
                        "url": "/ar/resize-image-to-2400x3000"
                    },
                    {
                        "name": "صورة تغيير الحجم إلى 2550x3300 ",
                        "iconSrc": "/img/resize.png",
                        "url": "/ar/resize-image-to-2550x3300"
                    },
                    {
                        "name": "صورة تغيير الحجم إلى 2700x4800 ",
                        "iconSrc": "/img/resize.png",
                        "url": "/ar/resize-image-to-2700x4800"
                    },
                    {
                        "name": "صورة تغيير الحجم إلى 3300x4200 ",
                        "iconSrc": "/img/resize.png",
                        "url": "/ar/resize-image-to-3300x4200"
                    },
                    {
                        "name": "صورة تغيير الحجم إلى 3300x4800 ",
                        "iconSrc": "/img/resize.png",
                        "url": "/ar/resize-image-to-3300x4800"
                    }
                ]
            }
        ]
    },
    "TEXTUAL_CONTENT": [],
    "HOW_TO_CONTENT": {
        "logoImageUrl": "/idea.svg",
        "heading": "كيفية تغيير حجم الصورة",
        "steps": [
            "قم بتحميل الصورة أو انقر فوق السهم المنسدل وحدد Dropbox/Google Drive لتحديد ملفك في المساحة المتوفرة.",
            "اضبط المعلمات للحصول على جودة صورة أفضل.\n",
            "اضغط على «معاينة» لإلقاء نظرة على التغييرات التي تم إجراؤها.",
            "احفظ التغييرات التي تم إجراؤها.",
            "مرحى!! الصورة جاهزة للاستخدام."
        ]
    },
 
    "jscdns": [
        "<script src=\"/assets/js/googledrive.js\"></script>",
        "<script src='https://cdnjs.cloudflare.com/ajax/libs/compressorjs/1.0.7/compressor.min.js' integrity='sha512-ZNlHFR9FBdeIlhwh040g5JmmYj7DQOwkqb9Y+DBJ1MaTzRMxKZkfHWkQU/dazDn9XRriajfh7ZGFksBKeUCsCg==' crossorigin='anonymous' referrerpolicy='no-referrer'></script>"
    ],
    "csscdns": [
        "<link rel=\"stylesheet\" href=\"/css/utils.css\" />",
        "<link rel=\"stylesheet\" href=\"/css/image-resize.css\" />"
    ]
}